README.md
setup.py
gaia_cmd_plotter/__init__.py
gaia_cmd_plotter/__version__.py
gaia_cmd_plotter/_config.py
gaia_cmd_plotter/gaia_cmd_axis.py
gaia_cmd_plotter.egg-info/PKG-INFO
gaia_cmd_plotter.egg-info/SOURCES.txt
gaia_cmd_plotter.egg-info/dependency_links.txt
gaia_cmd_plotter.egg-info/requires.txt
gaia_cmd_plotter.egg-info/top_level.txt
gaia_cmd_plotter/data/gaia_cmd.mplstyle
gaia_cmd_plotter/data/gaia_cmd_background.png