Metadata-Version: 2.1
Name: gaia-cmd-plotter
Version: 0.1.5
Summary: A Python package that provides a matplotlib.pyplot.Axes object that displays a Gaia CMD background.
Home-page: https://github.com/coryzh/gaia_cmd_plotter
Author: Yue Zhao
Author-email: Yue.Zhao@soton.ac.uk
Project-URL: Source Code, https://github.com/coryzh/gaia_cmd_plotter
Requires-Python: >=3.8
